geniartor/__init__.py
geniartor/__main__.py
geniartor/evaluation.py
geniartor/optimization.py
geniartor/piece.py
geniartor/rendering.py
geniartor/configs/default_config.yml
geniartor/configs/sinethesizer_presets.yml
tests/__init__.py
tests/conftest.py
tests/test_evaluation.py
tests/test_optimization.py
tests/test_piece.py
tests/test_rendering.py
geniartor-0.1.5.dist-info/LICENSE
geniartor-0.1.5.dist-info/METADATA
geniartor-0.1.5.dist-info/WHEEL
geniartor-0.1.5.dist-info/top_level.txt
geniartor-0.1.5.dist-info/RECORD
