Metadata-Version: 2.1
Name: geniartor
Version: 0.1.5
Summary: Music composition by optimizing of evaluational scores.
Home-page: https://github.com/Nikolay-Lysenko/geniartor
Author: Nikolay Lysenko
Author-email: nikolay-lysenco@yandex.ru
License: MIT
Keywords: ai_music,algorithmic_composition,generative_art
Platform: UNKNOWN
Classifier: Development Status :: 4 - Beta
Classifier: Intended Audience :: Developers
Classifier: Topic :: Artistic Software
Classifier: Topic :: Scientific/Engineering :: Artificial Intelligence
Classifier: License :: OSI Approved :: MIT License
Classifier: Programming Language :: Python :: 3
Requires-Python: >=3.6
License-File: LICENSE
Requires-Dist: pretty-midi
Requires-Dist: PyYAML
Requires-Dist: sinethesizer (<0.7,>=0.6)
